rdp_limited_edition/__about__.py
rdp_limited_edition/__init__.py
rdp_limited_edition/rdp.py
rdp_limited_edition-0.3.1.dist-info/METADATA
rdp_limited_edition-0.3.1.dist-info/WHEEL
rdp_limited_edition-0.3.1.dist-info/licenses/LICENSE.txt
rdp_limited_edition-0.3.1.dist-info/RECORD
