Metadata-Version: 2.3
Name: rdp-limited-edition
Version: 0.3.1
Summary: Ramer-Douglas-Peucker algorithm implementation with remaining points limit
Project-URL: Documentation, https://github.com/m-birke/rdp-limited-edition#readme
Project-URL: Issues, https://github.com/m-birke/rdp-limited-edition/issues
Project-URL: Source, https://github.com/m-birke/rdp-limited-edition
Author-email: m-birke <wesci@web.de>
License: MIT
Keywords: line simplification,ramer-douglas-peucker,rdp,simplification
Classifier: Development Status :: 4 - Beta
Classifier: Programming Language :: Python
Classifier: Programming Language :: Python :: 3.8
Classifier: Programming Language :: Python :: 3.9
Classifier: Programming Language :: Python :: 3.10
Classifier: Programming Language :: Python :: 3.11
Classifier: Programming Language :: Python :: 3.12
Classifier: Programming Language :: Python :: Implementation :: CPython
Classifier: Programming Language :: Python :: Implementation :: PyPy
Requires-Python: >=3.8
Requires-Dist: numpy
